radinNFP/__init__.py
radinNFP/radinNFP.py
NFP123456-0.0.1.dist-info/METADATA
NFP123456-0.0.1.dist-info/WHEEL
NFP123456-0.0.1.dist-info/top_level.txt
NFP123456-0.0.1.dist-info/RECORD
